ctprint/__init__.py
ctprint/ctprint.py
ctprint/help_message.py
LICENSE.txt
ctprint-0.1.8.dist-info/LICENSE.txt
ctprint-0.1.8.dist-info/WHEEL
ctprint-0.1.8.dist-info/METADATA
ctprint-0.1.8.dist-info/RECORD
