Metadata-Version: 2.1
Name: ctprint
Version: 0.1.8
Summary: coloring terminal output using '<tags> embedded in strings'
Home-page: https://github.com/saner99/ctprint
License: MIT
Keywords: color,colour,terminal,text,ansi,terminal,print,windows,crossplatform,xplatform,colorama,console,colorization,output,markup,logging,log,debug,debugging
Author: saner99
Author-email: it@saner99.ru
Requires-Python: >=3.6,<4.0
Classifier: Environment :: Console
Classifier: Intended Audience :: Developers
Classifier: License :: OSI Approved :: MIT License
Classifier: Operating System :: OS Independent
Classifier: Programming Language :: Python
Classifier: Programming Language :: Python :: 3
Classifier: Programming Language :: Python :: 3.10
Classifier: Programming Language :: Python :: 3.6
Classifier: Programming Language :: Python :: 3.7
Classifier: Programming Language :: Python :: 3.8
Classifier: Programming Language :: Python :: 3.9
Classifier: Topic :: Software Development :: Libraries :: Python Modules
Classifier: Topic :: Terminals
Requires-Dist: colorama (>=0.4.4,<0.5.0)
Project-URL: Repository, https://github.com/saner99/ctprint
